gh_env_manager/__init__.py
gh_env_manager/github_api_class.py
gh_env_manager/github_api_implementations.py
gh_env_manager/main.py
gh_env_manager/secret_variable_entity_class.py
gh_env_manager/yaml_env_class.py
gh_env_manager-0.4.1.dist-info/LICENSE
gh_env_manager-0.4.1.dist-info/METADATA
gh_env_manager-0.4.1.dist-info/WHEEL
gh_env_manager-0.4.1.dist-info/entry_points.txt
gh_env_manager-0.4.1.dist-info/RECORD
