Metadata-Version: 2.1
Name: gh-env-manager
Version: 0.4.1
Summary: A CLI tool to update GitHub Actions secrets and variables from a YAML file
Author: Antti Viitala
Author-email: tied02beaches@icloud.com
Requires-Python: >=3.9,<4.0
Classifier: Programming Language :: Python :: 3
Classifier: Programming Language :: Python :: 3.9
Classifier: Programming Language :: Python :: 3.10
Classifier: Programming Language :: Python :: 3.11
Requires-Dist: pynacl (>=1.5.0,<2.0.0)
Requires-Dist: pytest (>=7.2.1,<8.0.0)
Requires-Dist: pytest-cov (>=4.0.0,<5.0.0)
Requires-Dist: pyyaml (>=6.0,<7.0)
Requires-Dist: requests (>=2.28.2,<3.0.0)
Requires-Dist: typer[all] (>=0.7,<0.10)
